parse_utils/__init__.py
parse_utils/page_parser.py
parse_utils_yogen48-0.0.2.dist-info/LICENSE
parse_utils_yogen48-0.0.2.dist-info/METADATA
parse_utils_yogen48-0.0.2.dist-info/WHEEL
parse_utils_yogen48-0.0.2.dist-info/top_level.txt
parse_utils_yogen48-0.0.2.dist-info/RECORD
